.gitignore
.staticanalysis
.systemtests
.unittests
LICENSE
MANIFEST.in
README.md
developer-requirements.txt
name.txt
requirements.txt
setup.py
.vscode/settings.json
miscellaneous/coreutils_experiments/bypass_make_check_tests.py
muteria/README.md
muteria/__init__.py
muteria/_version.py
muteria.egg-info/PKG-INFO
muteria.egg-info/SOURCES.txt
muteria.egg-info/dependency_links.txt
muteria.egg-info/entry_points.txt
muteria.egg-info/requires.txt
muteria.egg-info/top_level.txt
muteria/__pycache__/__init__.cpython-39.pyc
muteria/__pycache__/_version.cpython-39.pyc
muteria/cli/README.md
muteria/cli/__init__.py
muteria/cli/cli.py
muteria/cli/run.sh
muteria/common/__init__.py
muteria/common/fs.py
muteria/common/matrices.py
muteria/common/mix.py
muteria/common/__pycache__/__init__.cpython-39.pyc
muteria/common/__pycache__/fs.cpython-39.pyc
muteria/common/__pycache__/matrices.cpython-39.pyc
muteria/common/__pycache__/mix.cpython-39.pyc
muteria/configmanager/__init__.py
muteria/configmanager/configurations.py
muteria/configmanager/helper.py
muteria/configmanager/__pycache__/__init__.cpython-39.pyc
muteria/configmanager/__pycache__/configurations.cpython-39.pyc
muteria/configmanager/__pycache__/helper.cpython-39.pyc
muteria/configmanager/defaults/__init__.py
muteria/configmanager/defaults/common_defaults.py
muteria/configmanager/defaults/extra_conf.py
muteria/configmanager/defaults/languages/README.md
muteria/configmanager/defaults/languages/__init__.py
muteria/controller/README.md
muteria/controller/__init__.py
muteria/controller/checkpoint_tasks.py
muteria/controller/executor.py
muteria/controller/explorer.py
muteria/controller/logging_setup.py
muteria/controller/main_controller.py
muteria/controller/__pycache__/__init__.cpython-39.pyc
muteria/controller/__pycache__/checkpoint_tasks.cpython-39.pyc
muteria/controller/__pycache__/executor.cpython-39.pyc
muteria/controller/__pycache__/explorer.cpython-39.pyc
muteria/controller/__pycache__/logging_setup.cpython-39.pyc
muteria/controller/__pycache__/main_controller.cpython-39.pyc
muteria/drivers/README.md
muteria/drivers/__init__.py
muteria/drivers/checkpoint_handler.py
