Metadata-Version: 2.1
Name: muteria
Version: 0.2.1
Summary: Software Analysis and Testing Framework
Home-page: https://github.com/muteria/muteria
Author: Thierry Titcheu Chekam
Author-email: thierry_tct@yahoo.com
License: UNKNOWN
Platform: UNKNOWN
Classifier: Development Status :: 3 - Alpha
Classifier: Natural Language :: English
Classifier: Intended Audience :: Science/Research
Classifier: Intended Audience :: Developers
Classifier: Topic :: Software Development :: Testing
Classifier: License :: OSI Approved :: MIT License
Classifier: Operating System :: OS Independent
Classifier: Operating System :: MacOS
Classifier: Operating System :: POSIX :: Linux
Classifier: Operating System :: POSIX :: BSD
Classifier: Programming Language :: Python
Classifier: Programming Language :: Python :: 3
Requires-Python: >3.3.0
License-File: LICENSE
